[
    {
        "nom": "Gniby",
        "region": "Kaffrine",
        "departement": ""
    },
    {
        "nom": "Katakel",
        "region": "Kaffrine",
        "departement": ""
    },
    {
        "nom": "Keur Mboucki",
        "region": "Kaffrine",
        "departement": ""
    },
    {
        "nom": "Mabo",
        "region": "Kaffrine",
        "departement": ""
    },
    {
        "nom": "Mbegue",
        "region": "Kaffrine",
        "departement": ""
    },
    {
        "nom": "Sagna",
        "region": "Kaffrine",
        "departement": ""
    }
]